tracerr.cpython-36m-x86_64-linux-gnu.so
tracerr-0.1.0.dist-info/top_level.txt
tracerr-0.1.0.dist-info/METADATA
tracerr-0.1.0.dist-info/RECORD
tracerr-0.1.0.dist-info/WHEEL
tracerr.libs/libprotobuf-d5400109.so.17.0.0
