Metadata-Version: 2.1
Name: tracerr
Version: 0.1.0
Summary: A simple raytracing program
Home-page: https://https://github.com/DLopezMadrid/tracerr
Author: Daniel Lopez Madrid, Zawar Qureshi
Author-email: qureshizawar@gmail.com
License: UNKNOWN
Keywords: raytracing
Platform: UNKNOWN
Classifier: Development Status :: 3 - Alpha
Classifier: Intended Audience :: Developers
Classifier: Topic :: Software Development
Classifier: License :: OSI Approved :: MIT License
Classifier: Programming Language :: Python :: 3.6
Classifier: Programming Language :: Python :: 3.7
Requires-Dist: protobuf
